Workbook

Sheet Wochenveranstaltung
M1: .

Sheet Filialumsätze
C1: Filialumsätze | M1: =Wochenveranstaltung!M1 -> .
A6: Filialumsätze | B6: Filiale 1 | C6: Filiale 2 | D6: Filiale 3 | E6: Filiale 4 | F6: Summe
A7: Quartal 1 | B7: 50000 | C7: 30000 | D7: 40000 | E7: 30000
A8: Quartal 2 | B8: 90000 | C8: 100000 | D8: 50000 | E8: 40000
A9: Quartal 3 | B9: 40000 | C9: 70000 | D9: 50000 | E9: 80000
A10: Quartal 4 | B10: 50000 | C10: 65000 | D10: 60000 | E10: 85000
A11: Summe

Sheet Verkäuferanalyse
A2: Verkäuferanalyse
M7: =Wochenveranstaltung!M1 -> .
A12: Wochentag | B12: Umsatz (€) | C12: Kundenzahl | D12: durchschnittlicher Umatz pro Kunde (€) | E12: Provision (€)
A13: Montag | B13: 5600 | C13: 12
A14: Dienstag | B14: 3800.7 | C14: 10
A15: Mittwoch | B15: 6600.75 | C15: 15
A16: Donnerstag | B16: 10400.8 | C16: 20
A17: Freitag | B17: 5500.8 | C17: 14
A18: Samstag | B18: 5385.25 | C18: 18
A19: Gesamt

Sheet Kraftstoffverbrauch
A1: Kraftstoffverbrauch | M1: =Wochenveranstaltung!M1 -> .
A13: Fahrzeug | B13: Tachostand bei Abfahrt (km) | C13: Tachostand bei Rückkehr (km) | D13: gefahrene km | E13: Nachfüllmenge bei Rückkehr (l) | F13: Verbrauch auf 100 km (l)
A14: MK-PC 1111 | B14: 54900 | C14: 55200 | E14: 30
A15: MK-PC 1112 | B15: 33600 | C15: 34200 | E15: 50
A16: MK-PC 1113 | B16: 45956 | C16: 46210 | E16: 28
A17: MK-PC 1114 | B17: 28907 | C17: 29706 | E17: 75

Sheet Filialkosten
C1: Filialkosten | M1: =Wochenveranstaltung!M1 -> .
A13: Standort | B13: Mietkosten/Monat | C13: Mietkosten/Jahr | D13: Nebenkosten/Jahr | E13: Gesamtkosten/Jahr
A14: Berlin | B14: 6000 | D14: 42000
A15: Bremen | B15: 4500 | D15: 30000
A16: Dortmund | B16: 3900 | D16: 28750
A17: Frankfurt | B17: 5800 | D17: 45350
A18: Hamburg | B18: 5500 | D18: 44000
A19: Leipzig | B19: 3200 | D19: 29670
A20: Lüdenscheid | B20: 7000 | D20: 55000
A21: Stuttgart | B21: 7200 | D21: 55500
A22: Gesamt:

Sheet Lagerbestand
B1: Lagerbestände | M1: =Wochenveranstaltung!M1 -> .
A8: Art.-Nr. | B8: 140111 | C8: 140112 | D8: 140113 | E8: 140114
A9: Artikelbezeichnung | B9: Wheel-Maus | C9: Turbo-Maus | D9: Optische Maus | E9: Design-Maus
A10: Anfangsbestand
A11: Zugänge
A12: Abgänge
A13: aktueller Lagerbestand

Sheet Grundstückskauf
D1: Grundstückskauf
M5: =Wochenveranstaltung!M1 -> .
A10: Angebot Nr. | B10: Länge (m) | C10: Breite (m) | D10: Umfang (m) | E10: gesamte Größe (m²) | F10: Kaufpreis (€) | G10: Preis pro m² (€)
A11: 1 | B11: 42.24 | C11: 18.4
A12: 2 | B12: 37 | C12: 21.5
A13: 3 | B13: 26.5 | C13: 29
A14: 4 | B14: 30.82 | C14: 23.7

Sheet Gehaltsermittlung
D1: Gehaltsermittlung | M1: =Wochenveranstaltung!M1 -> .
A9: Name | B9: Brutto-gehalt | C9: Lohn-steuer | D9: Solidaritäts-zuschlag | E9: Kirchen-steuer | F9: Renten-versicherung AN-Anteil | G9: Kranken-versicherung AN-Anteil | H9: Pflege-versicherung AN-Anteil | I9: Arbeitslosen-versicherung AN-Anteil | J9: Abzüge insgesamt | K9: Abzüge in % vom Bruttogehalt | L9: Netto-gehalt
A10: Wolf | B10: 2970 | C10: 412.67 | D10: 13.65 | E10: 37.14 | F10: 289.58 | G10: 207.9 | H10: 25.25 | I10: 96.53
A11: Alt | B11: 1293.42 | C11: 131.04 | D11: 7.21 | E11: 11.79 | F11: 126.11 | G11: 89.89 | H11: 10.99 | I11: 42.04
A12: Wild | B12: 1474 | C12: 124.71 | D12: 0 | E12: 0 | F12: 143.72 | G12: 103.18 | H12: 12.53 | I12: 47.91
A13: Voss | B13: 1852 | C13: 308 | D13: 16.94 | E13: 27.72 | F13: 180.57 | G13: 134.27 | H13: 15.74 | I13: 60.19

Sheet L1
C1: Wochenveranstaltungen im Konzertsaal
B3: Veranstaltung | C3: Preis pro Karte | D3: Karten insgesamt | E3: verkaufte Karten | F3: freie Plätze | G3: Umsatz
A4: Montag | B4: Klassik 1 | C4: 75 | D4: 2000 | E4: 1170 | F4: =D4-E4 -> 830 | G4: =C4*E4 -> 87750
A5: Dienstag | B5: Klassik 2 | C5: 85 | D5: 3000 | E5: 2148 | F5: =D5-E5 -> 852 | G5: =C5*E5 -> 182580
A6: Mittwoch | B6: Pop 1 | C6: 40 | D6: 2500 | E6: 2500 | F6: =D6-E6 -> 0 | G6: =C6*E6 -> 100000
A7: Donnerstag | B7: Pop 2 | C7: 55 | D7: 2500 | E7: 1879 | F7: =D7-E7 -> 621 | G7: =C7*E7 -> 103345
A8: Freitag | B8: Rock 1 | C8: 35 | D8: 2000 | E8: 760 | F8: =D8-E8 -> 1240 | G8: =C8*E8 -> 26600
A9: Samstag | B9: Rock 2 | C9: 80 | D9: 2500 | E9: 2370 | F9: =D9-E9 -> 130 | G9: =C9*E9 -> 189600
A10: Summen: | D10: =SUM(D4:D9) -> 14500 | E10: =SUM(E4:E9) -> 10827 | F10: =SUM(F4:F9) -> 3673 | G10: =SUM(G4:G9) -> 689875

Sheet L2
A6: Filialumsätze | B6: Filiale 1 | C6: Filiale 2 | D6: Filiale 3 | E6: Filiale 4 | F6: Summe
A7: Quartal 1 | B7: 50000 | C7: 30000 | D7: 40000 | E7: 30000 | F7: =SUM(B7:E7) -> 150000
A8: Quartal 2 | B8: 90000 | C8: 100000 | D8: 50000 | E8: 40000 | F8: =SUM(B8:E8) -> 280000
A9: Quartal 3 | B9: 40000 | C9: 70000 | D9: 50000 | E9: 80000 | F9: =SUM(B9:E9) -> 240000
A10: Quartal 4 | B10: 50000 | C10: 65000 | D10: 60000 | E10: 85000 | F10: =SUM(B10:E10) -> 260000
A11: Summe | B11: =SUM(B7:B10) -> 230000 | C11: =SUM(C7:C10) -> 265000 | D11: =SUM(D7:D10) -> 200000 | E11: =SUM(E7:E10) -> 235000

Sheet L3
A12: Wochentag | B12: Umsatz (€) | C12: Kundenzahl | D12: durchschnittlicher Umatz pro Kunde (€) | E12: Provision (€)
A13: Montag | B13: 5600 | C13: 12 | D13: =B13/C13 -> 466.66667 | E13: =B13*2/100 -> 112
A14: Dienstag | B14: 3800.7 | C14: 10 | D14: =B14/C14 -> 380.07 | E14: =B14*2/100 -> 76.014
A15: Mittwoch | B15: 6600.75 | C15: 15 | D15: =B15/C15 -> 440.05 | E15: =B15*2/100 -> 132.015
A16: Donnerstag | B16: 10400.8 | C16: 20 | D16: =B16/C16 -> 520.04 | E16: =B16*2/100 -> 208.016
A17: Freitag | B17: 5500.8 | C17: 14 | D17: =B17/C17 -> 392.91429 | E17: =B17*2/100 -> 110.016
A18: Samstag | B18: 5385.25 | C18: 18 | D18: =B18/C18 -> 299.18056 | E18: =B18*2/100 -> 107.705
A19: Gesamt | B19: =SUM(B13:B18) -> 37288.3 | C19: =SUM(C13:C18) -> 89 | D19: =B19/C19 -> 418.96966 | E19: =B19*2/100 -> 745.766

Sheet L4
A13: Fahrzeug | B13: Tachostand bei Abfahrt (km) | C13: Tachostand bei Rückkehr (km) | D13: gefahrene km | E13: Nachfüllmenge bei Rückkehr (l) | F13: Verbrauch auf 100 km (l)
A14: MK-PC 1111 | B14: 54900 | C14: 55200 | D14: =C14-B14 -> 300 | E14: 30 | F14: =E14/D14*100 -> 10
A15: MK-PC 1112 | B15: 33600 | C15: 34200 | D15: =C15-B15 -> 600 | E15: 50 | F15: =E15/D15*100 -> 8.3333333
A16: MK-PC 1113 | B16: 45956 | C16: 46210 | D16: =C16-B16 -> 254 | E16: 28 | F16: =E16/D16*100 -> 11.023622
A17: MK-PC 1114 | B17: 28907 | C17: 29706 | D17: =C17-B17 -> 799 | E17: 75 | F17: =E17/D17*100 -> 9.3867334

Sheet L5
A13: Standort | B13: Mietkosten/Monat | C13: Mietkosten/Jahr | D13: Nebenkosten/Jahr | E13: Gesamtkosten/Jahr
A14: Berlin | B14: 6000 | C14: =B14*12 -> 72000 | D14: 42000 | E14: =C14+D14 -> 114000
A15: Bremen | B15: 4500 | C15: =B15*12 -> 54000 | D15: 30000 | E15: =C15+D15 -> 84000
A16: Dortmund | B16: 3900 | C16: =B16*12 -> 46800 | D16: 28750 | E16: =C16+D16 -> 75550
A17: Frankfurt | B17: 5800 | C17: =B17*12 -> 69600 | D17: 45350 | E17: =C17+D17 -> 114950
A18: Hamburg | B18: 5500 | C18: =B18*12 -> 66000 | D18: 44000 | E18: =C18+D18 -> 110000
A19: Lüdenscheid | B19: 3200 | C19: =B19*12 -> 38400 | D19: 29670 | E19: =C19+D19 -> 68070
A20: München | B20: 7000 | C20: =B20*12 -> 84000 | D20: 55000 | E20: =C20+D20 -> 139000
A21: Stuttgart | B21: 7200 | C21: =B21*12 -> 86400 | D21: 55500 | E21: =C21+D21 -> 141900
A22: Gesamt: | B22: =SUM(B14:B21) -> 43100 | C22: =SUM(C14:C21) -> 517200 | D22: =SUM(D14:D21) -> 330270 | E22: =SUM(E14:E21) -> 847470

Sheet L6
A8: Art.-Nr. | B8: 140111 | C8: 140112 | D8: 140113 | E8: 140114
A9: Artikelbezeichnung | B9: Wheel-Maus | C9: Turbo-Maus | D9: Optische Maus | E9: Design-Maus
A10: Anfangsbestand | B10: 90 | C10: 40 | D10: 65 | E10: 33
A11: Zugänge | B11: 30 | C11: 0 | D11: 25 | E11: 10
A12: Abgänge | B12: 45 | C12: 40 | D12: 45 | E12: 8
A13: aktueller Lagerbestand | B13: =B10+B11-B12 -> 75 | C13: =C10+C11-C12 -> 0 | D13: =D10+D11-D12 -> 45 | E13: =E10+E11-E12 -> 35

Sheet L7
A10: Angebot Nr. | B10: Länge (m) | C10: Breite (m) | D10: Umfang (m) | E10: gesamte Größe (m²) | F10: Kaufpreis (€) | G10: Preis pro m² (€)
A11: 1 | B11: 42.24 | C11: 18.4 | D11: =2*B11+2*C11 -> 121.28 | E11: =B11*C11 -> 777.216 | F11: 19430 | G11: =F11/E11 -> 24.999485
A12: 2 | B12: 37 | C12: 21.5 | D12: =2*B12+2*C12 -> 117 | E12: =B12*C12 -> 795.5 | F12: 20683 | G12: =F12/E12 -> 26
A13: 3 | B13: 26.5 | C13: 29 | D13: =2*B13+2*C13 -> 111 | E13: =B13*C13 -> 768.5 | F13: 20604.5 | G13: =F13/E13 -> 26.811321
A14: 4 | B14: 30.82 | C14: 23.7 | D14: =2*B14+2*C14 -> 109.04 | E14: =B14*C14 -> 730.434 | F14: 18406 | G14: =F14/E14 -> 25.198717

Sheet L8
A9: Name | B9: Brutto-gehalt | C9: Lohn-steuer | D9: Solidaritäts-zuschlag | E9: Kirchen-steuer | F9: Renten-versicherung AN-Anteil | G9: Kranken-versicherung AN-Anteil | H9: Pflege-versicherung AN-Anteil | I9: Arbeitslosen-versicherung AN-Anteil | J9: Abzüge insgesamt | K9: Abzüge in % vom Bruttogehalt | L9: Netto-gehalt
A10: Wolf | B10: 2970 | C10: 412.67 | D10: 13.65 | E10: 37.14 | F10: 289.58 | G10: 207.9 | H10: 25.25 | I10: 96.53 | J10: =SUM(C10:I10) -> 1082.72 | K10: =J10/B10*100 -> 36.455219 | L10: =B10-J10 -> 1887.28
A11: Alt | B11: 1293.42 | C11: 131.04 | D11: 7.21 | E11: 11.79 | F11: 126.11 | G11: 89.89 | H11: 10.99 | I11: 42.04 | J11: =SUM(C11:I11) -> 419.07 | K11: =J11/B11*100 -> 32.400148 | L11: =B11-J11 -> 874.35
A12: Wild | B12: 1474 | C12: 124.71 | D12: 0 | E12: 0 | F12: 143.72 | G12: 103.18 | H12: 12.53 | I12: 47.91 | J12: =SUM(C12:I12) -> 432.05 | K12: =J12/B12*100 -> 29.311398 | L12: =B12-J12 -> 1041.95
A13: Voss | B13: 1852 | C13: 308 | D13: 16.94 | E13: 27.72 | F13: 180.57 | G13: 134.27 | H13: 15.74 | I13: 60.19 | J13: =SUM(C13:I13) -> 743.43 | K13: =J13/B13*100 -> 40.142009 | L13: =B13-J13 -> 1108.57
